pygpsclient/__init__.py
pygpsclient/__main__.py
pygpsclient/_version.py
pygpsclient/about_dialog.py
pygpsclient/app.py
pygpsclient/banner_frame.py
pygpsclient/canvas_map.py
pygpsclient/canvas_subclasses.py
pygpsclient/chart_frame.py
pygpsclient/configuration.py
pygpsclient/confirm_box.py
pygpsclient/console_frame.py
pygpsclient/dialog_state.py
pygpsclient/dynamic_config_frame.py
pygpsclient/file_handler.py
pygpsclient/globals.py
pygpsclient/gnss_status.py
pygpsclient/gpx_dialog.py
pygpsclient/hardware_info_frame.py
pygpsclient/helpers.py
pygpsclient/importmap_dialog.py
pygpsclient/imu_frame.py
pygpsclient/init_presets.py
pygpsclient/levelsview_frame.py
pygpsclient/map_frame.py
pygpsclient/mapquest_handler.py
pygpsclient/menu_bar.py
pygpsclient/nmea_config_dialog.py
pygpsclient/nmea_handler.py
pygpsclient/nmea_preset_frame.py
pygpsclient/ntrip_client_dialog.py
pygpsclient/qgc_handler.py
pygpsclient/receiver_config_handler.py
pygpsclient/recorder_dialog.py
pygpsclient/rover_frame.py
pygpsclient/rtcm3_handler.py
pygpsclient/sbf_handler.py
pygpsclient/scatter_frame.py
pygpsclient/serialconfig_frame.py
pygpsclient/serialconfig_lband_frame.py
pygpsclient/serverconfig_dialog.py
pygpsclient/settings_child_frame.py
pygpsclient/settings_dialog.py
pygpsclient/settings_frame.py
pygpsclient/signalsview_frame.py
pygpsclient/skyview_frame.py
pygpsclient/socketconfig_frame.py
pygpsclient/socketconfig_ntrip_frame.py
pygpsclient/spartn_dialog.py
pygpsclient/spartn_gnss_frame.py
pygpsclient/spartn_json_config.py
pygpsclient/spartn_lband_frame.py
pygpsclient/spartn_mqtt_frame.py
pygpsclient/spectrum_frame.py
pygpsclient/sqlite_handler.py
pygpsclient/status_frame.py
pygpsclient/stream_handler.py
pygpsclient/strings.py
pygpsclient/sysmon_frame.py
pygpsclient/toplevel_dialog.py
pygpsclient/tty_handler.py
pygpsclient/tty_preset_dialog.py
pygpsclient/ubx_cfgval_frame.py
pygpsclient/ubx_config_dialog.py
pygpsclient/ubx_handler.py
pygpsclient/ubx_msgrate_frame.py
pygpsclient-1.6.2.dist-info/licenses/LICENSE
pygpsclient-1.6.2.dist-info/METADATA
pygpsclient-1.6.2.dist-info/WHEEL
pygpsclient-1.6.2.dist-info/entry_points.txt
pygpsclient-1.6.2.dist-info/top_level.txt
pygpsclient-1.6.2.dist-info/RECORD
