Metadata-Version: 2.4
Name: pygpsclient
Version: 1.6.2
Summary: GNSS Diagnostic and UBX Configuration GUI Application
Author-email: Steve Smith <semuadmin@semuconsulting.com>
Maintainer-email: Steve Smith <semuadmin@semuconsulting.com>
License-Expression: BSD-3-Clause
Project-URL: homepage, https://github.com/semuconsulting/PyGPSClient
Project-URL: documentation, https://www.semuconsulting.com/pygpsclient/
Project-URL: repository, https://github.com/semuconsulting/PyGPSClient
Project-URL: changelog, https://github.com/semuconsulting/PyGPSClient/blob/master/RELEASE_NOTES.md
Keywords: PyGPSClient,GNSS,GPS,GALILEO,GLONASS,BEIDOU,NMEA,UBX,RTCM,NTRIP,SPARTN,RTK,DGPS,u-center
Classifier: Operating System :: OS Independent
Classifier: Development Status :: 5 - Production/Stable
Classifier: Environment :: MacOS X
Classifier: Environment :: Win32 (MS Windows)
Classifier: Environment :: X11 Applications
Classifier: Environment :: Console
Classifier: Intended Audience :: Developers
Classifier: Intended Audience :: Science/Research
Classifier: Intended Audience :: End Users/Desktop
Classifier: Programming Language :: Python :: 3
Classifier: Programming Language :: Python :: 3.10
Classifier: Programming Language :: Python :: 3.11
Classifier: Programming Language :: Python :: 3.12
Classifier: Programming Language :: Python :: 3.13
Classifier: Programming Language :: Python :: 3.14
Classifier: Topic :: Utilities
Classifier: Topic :: Software Development :: Libraries :: Python Modules
Classifier: Topic :: Scientific/Engineering :: GIS
Requires-Python: >=3.10
License-File: LICENSE
Requires-Dist: requests>=2.28.0
Requires-Dist: Pillow>=9.0.0
Requires-Dist: pygnssutils>=1.1.21
Dynamic: license-file
